fpos/__init__.py
fpos/_modidx.py
fpos/core.py
fpos-0.0.2.dist-info/LICENSE
fpos-0.0.2.dist-info/METADATA
fpos-0.0.2.dist-info/WHEEL
fpos-0.0.2.dist-info/entry_points.txt
fpos-0.0.2.dist-info/top_level.txt
fpos-0.0.2.dist-info/RECORD
