Metadata-Version: 2.1
Name: fpos
Version: 0.0.2
Summary: fpos
Home-page: https://github.com/dsm-72/fpos
Author: dsm-72
Author-email: sumner.magruder@yale.edu
License: Apache Software License 2.0
Keywords: fpos
Classifier: Development Status :: 4 - Beta
Classifier: Intended Audience :: Developers
Classifier: Natural Language :: English
Classifier: Programming Language :: Python :: 3.11
Classifier: License :: OSI Approved :: Apache Software License
Requires-Python: >=3.11
License-File: LICENSE
Requires-Dist: nchr
Requires-Dist: nlit
Requires-Dist: chck
Requires-Dist: quac
Requires-Dist: atup
Provides-Extra: dev
